<annotation>
  <folder>input</folder>
  <filename>1677917169.jpg</filename>
  <path>E:\OpenLabeling\main\input\1677917169.jpg</path>
  <source>
    <database>Unknown</database>
  </source>
  <size>
    <width>2412</width>
    <height>1421</height>
    <depth>3</depth>
  </size>
  <segmented>0</segmented>
  <object>
    <name>tree</name>
    <pose>Unspecified</pose>
    <truncated>0</truncated>
    <difficult>0</difficult>
    <bndbox>
      <xmin>1439</xmin>
      <ymin>516</ymin>
      <xmax>1485</xmax>
      <ymax>660</ymax>
    </bndbox>
  </object>
  <object>
    <name>tree</name>
    <pose>Unspecified</pose>
    <truncated>0</truncated>
    <difficult>0</difficult>
    <bndbox>
      <xmin>1798</xmin>
      <ymin>520</ymin>
      <xmax>1853</xmax>
      <ymax>667</ymax>
    </bndbox>
  </object>
  <object>
    <name>tree</name>
    <pose>Unspecified</pose>
    <truncated>0</truncated>
    <difficult>0</difficult>
    <bndbox>
      <xmin>2014</xmin>
      <ymin>537</ymin>
      <xmax>2053</xmax>
      <ymax>635</ymax>
    </bndbox>
  </object>
  <object>
    <name>tree</name>
    <pose>Unspecified</pose>
    <truncated>0</truncated>
    <difficult>0</difficult>
    <bndbox>
      <xmin>825</xmin>
      <ymin>380</ymin>
      <xmax>923</xmax>
      <ymax>649</ymax>
    </bndbox>
  </object>
</annotation>
